aiopenid/__init__.py
aiopenid/oauth2.py
aiopenid-0.1.0.dist-info/METADATA
aiopenid-0.1.0.dist-info/WHEEL
aiopenid-0.1.0.dist-info/RECORD
