Metadata-Version: 2.1
Name: aiopenid
Version: 0.1.0
Summary: 
Author: None
Requires-Python: >=3.10,<4.0
Classifier: Programming Language :: Python :: 3
Classifier: Programming Language :: Python :: 3.10
Classifier: Programming Language :: Python :: 3.11
Classifier: Programming Language :: Python :: 3.12
Requires-Dist: httpx (>=0.27.0,<0.28.0)
Requires-Dist: python-jose[cryptography] (>=3.3.0,<4.0.0)
